[{"date":"Jan 2000","price":"1394.46","other":"394"},{"date":"Feb 2000","price":"1366.42","other":"366"},{"date":"Mar 2000","price":"1498.58","other":"498"},{"date":"Apr 2000","price":"1452.43","other":"452"},{"date":"May 2000","price":"1420.6","other":"420"},{"date":"Jun 2000","price":"1454.6","other":"454"},{"date":"Jul 2000","price":"1430.83","other":"430"},{"date":"Aug 2000","price":"1517.68","other":"517"},{"date":"Sep 2000","price":"1436.51","other":"436"},{"date":"Oct 2000","price":"1429.4","other":"429"},{"date":"Nov 2000","price":"1314.95","other":"314"},{"date":"Dec 2000","price":"1320.28","other":"320"},{"date":"Jan 2001","price":"1366.01","other":"366"},{"date":"Feb 2001","price":"1239.94","other":"239"},{"date":"Mar 2001","price":"1160.33","other":"160"},{"date":"Apr 2001","price":"1249.46","other":"249"},{"date":"May 2001","price":"1255.82","other":"255"},{"date":"Jun 2001","price":"1224.38","other":"224"},{"date":"Jul 2001","price":"1211.23","other":"211"},{"date":"Aug 2001","price":"1133.58","other":"133"},{"date":"Sep 2001","price":"1040.94","other":"040"},{"date":"Oct 2001","price":"1059.78","other":"059"},{"date":"Nov 2001","price":"1139.45","other":"139"},{"date":"Dec 2001","price":"1148.08","other":"148"},{"date":"Jan 2002","price":"1130.2","other":"130"},{"date":"Feb 2002","price":"1106.73","other":"106"},{"date":"Mar 2002","price":"1147.39","other":"147"},{"date":"Apr 2002","price":"1076.92","other":"076"},{"date":"May 2002","price":"1067.14","other":"067"},{"date":"Jun 2002","price":"989.82","other":"989"},{"date":"Jul 2002","price":"911.62","other":"911"},{"date":"Aug 2002","price":"916.07","other":"916"},{"date":"Sep 2002","price":"815.28","other":"815"},{"date":"Oct 2002","price":"885.76","other":"885"},{"date":"Nov 2002","price":"936.31","other":"936"},{"date":"Dec 2002","price":"879.82","other":"879"},{"date":"Jan 2003","price":"855.7","other":"855"},{"date":"Feb 2003","price":"841.15","other":"841"},{"date":"Mar 2003","price":"848.18","other":"848"},{"date":"Apr 2003","price":"916.92","other":"916"},{"date":"May 2003","price":"963.59","other":"963"},{"date":"Jun 2003","price":"974.5","other":"974"},{"date":"Jul 2003","price":"990.31","other":"990"},{"date":"Aug 2003","price":"1008.01","other":"1008"},{"date":"Sep 2003","price":"995.97","other":"995"},{"date":"Oct 2003","price":"1050.71","other":"1050"},{"date":"Nov 2003","price":"1058.2","other":"1058"},{"date":"Dec 2003","price":"1111.92","other":"1111"},{"date":"Jan 2004","price":"1131.13","other":"1131"},{"date":"Feb 2004","price":"1144.94","other":"1144"},{"date":"Mar 2004","price":"1126.21","other":"1126"},{"date":"Apr 2004","price":"1107.3","other":"1107"},{"date":"May 2004","price":"1120.68","other":"1120"},{"date":"Jun 2004","price":"1140.84","other":"1140"},{"date":"Jul 2004","price":"1101.72","other":"1101"},{"date":"Aug 2004","price":"1104.24","other":"1104"},{"date":"Sep 2004","price":"1114.58","other":"1114"},{"date":"Oct 2004","price":"1130.2","other":"1130"},{"date":"Nov 2004","price":"1173.82","other":"1173"},{"date":"Dec 2004","price":"1211.92","other":"1211"},{"date":"Jan 2005","price":"1181.27","other":"1181"},{"date":"Feb 2005","price":"1203.6","other":"1203"},{"date":"Mar 2005","price":"1180.59","other":"1180"},{"date":"Apr 2005","price":"1156.85","other":"1156"},{"date":"May 2005","price":"1191.5","other":"1191"},{"date":"Jun 2005","price":"1191.33","other":"1191"},{"date":"Jul 2005","price":"1234.18","other":"1234"},{"date":"Aug 2005","price":"1220.33","other":"1220"},{"date":"Sep 2005","price":"1228.81","other":"1228"},{"date":"Oct 2005","price":"1207.01","other":"1207"},{"date":"Nov 2005","price":"1249.48","other":"1249"},{"date":"Dec 2005","price":"1248.29","other":"1248"},{"date":"Jan 2006","price":"1280.08","other":"1280"},{"date":"Feb 2006","price":"1280.66","other":"1280"},{"date":"Mar 2006","price":"1294.87","other":"1294"},{"date":"Apr 2006","price":"1310.61","other":"1310"},{"date":"May 2006","price":"1270.09","other":"1270"},{"date":"Jun 2006","price":"1270.2","other":"1270"},{"date":"Jul 2006","price":"1276.66","other":"1276"},{"date":"Aug 2006","price":"1303.82","other":"1303"},{"date":"Sep 2006","price":"1335.85","other":"1335"},{"date":"Oct 2006","price":"1377.94","other":"1377"},{"date":"Nov 2006","price":"1400.63","other":"1400"},{"date":"Dec 2006","price":"1418.3","other":"1418"},{"date":"Jan 2007","price":"1438.24","other":"1438"},{"date":"Feb 2007","price":"1406.82","other":"1406"},{"date":"Mar 2007","price":"1420.86","other":"1420"},{"date":"Apr 2007","price":"1482.37","other":"1482"},{"date":"May 2007","price":"1530.62","other":"1530"},{"date":"Jun 2007","price":"1503.35","other":"1503"},{"date":"Jul 2007","price":"1455.27","other":"1455"},{"date":"Aug 2007","price":"1473.99","other":"1473"},{"date":"Sep 2007","price":"1526.75","other":"1526"},{"date":"Oct 2007","price":"1549.38","other":"1549"},{"date":"Nov 2007","price":"1481.14","other":"1481"},{"date":"Dec 2007","price":"1468.36","other":"1468"},{"date":"Jan 2008","price":"1378.55","other":"1378"},{"date":"Feb 2008","price":"1330.63","other":"1330"},{"date":"Mar 2008","price":"1322.7","other":"1322"},{"date":"Apr 2008","price":"1385.59","other":"1385"},{"date":"May 2008","price":"1400.38","other":"1400"},{"date":"Jun 2008","price":"1280","other":"1280"},{"date":"Jul 2008","price":"1267.38","other":"1267"},{"date":"Aug 2008","price":"1282.83","other":"1282"},{"date":"Sep 2008","price":"1166.36","other":"1166"},{"date":"Oct 2008","price":"968.75","other":"968"},{"date":"Nov 2008","price":"896.24","other":"896"},{"date":"Dec 2008","price":"903.25","other":"903"},{"date":"Jan 2009","price":"825.88","other":"825"},{"date":"Feb 2009","price":"735.09","other":"735"},{"date":"Mar 2009","price":"797.87","other":"797"},{"date":"Apr 2009","price":"872.81","other":"872"},{"date":"May 2009","price":"919.14","other":"919"},{"date":"Jun 2009","price":"919.32","other":"919"},{"date":"Jul 2009","price":"987.48","other":"987"},{"date":"Aug 2009","price":"1020.62","other":"102"},{"date":"Sep 2009","price":"1057.08","other":"105"},{"date":"Oct 2009","price":"1036.19","other":"103"},{"date":"Nov 2009","price":"1095.63","other":"109"},{"date":"Dec 2009","price":"1115.1","other":"111"},{"date":"Jan 2010","price":"1073.87","other":"107"},{"date":"Feb 2010","price":"1104.49","other":"110"},{"date":"Mar 2010","price":"1140.45","other":"114"}]